[
    {
        "ticker": "DLR/ABR26",
        "bid": 1405.5,
        "offer": 1406.0,
        "last": 1399.0,
        "timestamp": "2026-04-08T14:51:12.879995"
    },
    {
        "ticker": "DLR/MAY26",
        "bid": 1431.5,
        "offer": 1432.5,
        "last": "S/D",
        "timestamp": "2026-04-08T14:51:12.879995"
    },
    {
        "ticker": "DLR/JUN26",
        "bid": 1462.5,
        "offer": 1464.0,
        "last": "S/D",
        "timestamp": "2026-04-08T14:51:12.879995"
    },
    {
        "ticker": "DLR/JUL26",
        "bid": 1496.0,
        "offer": 1498.5,
        "last": 1499.5,
        "timestamp": "2026-04-08T14:51:12.879995"
    },
    {
        "ticker": "DLR/AGO26",
        "bid": 1520.0,
        "offer": 1533.0,
        "last": "S/D",
        "timestamp": "2026-04-08T14:51:12.879995"
    },
    {
        "ticker": "DLR/OCT26",
        "bid": 1590.0,
        "offer": "S/D",
        "last": "S/D",
        "timestamp": "2026-04-08T14:51:12.879995"
    },
    {
        "ticker": "DLR/NOV26",
        "bid": "S/D",
        "offer": "S/D",
        "last": "S/D",
        "timestamp": "2026-04-08T14:51:12.879995"
    },
    {
        "ticker": "DLR/ENE27",
        "bid": 1675.0,
        "offer": 1698.0,
        "last": "S/D",
        "timestamp": "2026-04-08T14:51:12.879995"
    },
    {
        "ticker": "DLR/FEB27",
        "bid": "S/D",
        "offer": "S/D",
        "last": "S/D",
        "timestamp": "2026-04-08T14:51:12.879995"
    },
    {
        "ticker": "DLR/MAR27",
        "bid": "S/D",
        "offer": "S/D",
        "last": "S/D",
        "timestamp": "2026-04-08T14:51:12.879995"
    }
]