[
    {
        "ticker": "DLR/ABR26",
        "bid": 1384.0,
        "offer": 1384.5,
        "last": 1384.5,
        "timestamp": "2026-04-22T17:29:25.917112"
    },
    {
        "ticker": "DLR/MAY26",
        "bid": 1406.0,
        "offer": 1407.0,
        "last": "S/D",
        "timestamp": "2026-04-22T17:29:25.917112"
    },
    {
        "ticker": "DLR/JUN26",
        "bid": 1433.0,
        "offer": 1434.5,
        "last": "S/D",
        "timestamp": "2026-04-22T17:29:25.917112"
    },
    {
        "ticker": "DLR/JUL26",
        "bid": 1461.0,
        "offer": 1463.5,
        "last": 1451.0,
        "timestamp": "2026-04-22T17:29:25.917112"
    },
    {
        "ticker": "DLR/AGO26",
        "bid": 1489.5,
        "offer": 1493.5,
        "last": "S/D",
        "timestamp": "2026-04-22T17:29:25.917112"
    },
    {
        "ticker": "DLR/OCT26",
        "bid": 1546.5,
        "offer": 1551.5,
        "last": "S/D",
        "timestamp": "2026-04-22T17:29:25.917112"
    },
    {
        "ticker": "DLR/NOV26",
        "bid": 1570.0,
        "offer": 1585.0,
        "last": "S/D",
        "timestamp": "2026-04-22T17:29:25.917112"
    },
    {
        "ticker": "DLR/ENE27",
        "bid": 1630.0,
        "offer": 1645.0,
        "last": "S/D",
        "timestamp": "2026-04-22T17:29:25.917112"
    },
    {
        "ticker": "DLR/FEB27",
        "bid": 1630.0,
        "offer": 1633.0,
        "last": 1633.0,
        "timestamp": "2026-04-22T17:29:25.917112"
    },
    {
        "ticker": "DLR/MAR27",
        "bid": 1660.0,
        "offer": 1720.0,
        "last": "S/D",
        "timestamp": "2026-04-22T17:29:25.917112"
    }
]