[
    {
        "ticker": "DLR/ABR26",
        "bid": 1416.5,
        "offer": 1417.0,
        "last": 1416.5,
        "timestamp": "2026-04-07T14:51:16.738132"
    },
    {
        "ticker": "DLR/MAY26",
        "bid": 1442.0,
        "offer": 1443.0,
        "last": "S/D",
        "timestamp": "2026-04-07T14:51:16.738132"
    },
    {
        "ticker": "DLR/JUN26",
        "bid": 1473.0,
        "offer": 1474.0,
        "last": "S/D",
        "timestamp": "2026-04-07T14:51:16.738132"
    },
    {
        "ticker": "DLR/JUL26",
        "bid": 1505.0,
        "offer": 1506.0,
        "last": 1510.0,
        "timestamp": "2026-04-07T14:51:16.738132"
    },
    {
        "ticker": "DLR/AGO26",
        "bid": 1535.5,
        "offer": 1542.0,
        "last": "S/D",
        "timestamp": "2026-04-07T14:51:16.738132"
    },
    {
        "ticker": "DLR/OCT26",
        "bid": 1603.0,
        "offer": 1606.0,
        "last": "S/D",
        "timestamp": "2026-04-07T14:51:16.738132"
    },
    {
        "ticker": "DLR/NOV26",
        "bid": 1628.0,
        "offer": 1646.0,
        "last": "S/D",
        "timestamp": "2026-04-07T14:51:16.738132"
    },
    {
        "ticker": "DLR/ENE27",
        "bid": "S/D",
        "offer": "S/D",
        "last": "S/D",
        "timestamp": "2026-04-07T14:51:16.738132"
    },
    {
        "ticker": "DLR/FEB27",
        "bid": "S/D",
        "offer": "S/D",
        "last": "S/D",
        "timestamp": "2026-04-07T14:51:16.738132"
    },
    {
        "ticker": "DLR/MAR27",
        "bid": "S/D",
        "offer": "S/D",
        "last": "S/D",
        "timestamp": "2026-04-07T14:51:16.738132"
    }
]