[
    {
        "ticker": "DLR/JUN26",
        "bid": "S/D",
        "offer": "S/D",
        "last": "S/D",
        "timestamp": "2026-06-30T16:21:08.412818"
    },
    {
        "ticker": "DLR/JUL26",
        "bid": 1508.5,
        "offer": 1509.0,
        "last": 1509.5,
        "timestamp": "2026-06-30T16:21:08.412818"
    },
    {
        "ticker": "DLR/AGO26",
        "bid": 1536.5,
        "offer": 1537.0,
        "last": 1541.0,
        "timestamp": "2026-06-30T16:21:08.412818"
    },
    {
        "ticker": "DLR/OCT26",
        "bid": "S/D",
        "offer": 1478.0,
        "last": 1473.0,
        "timestamp": "2026-06-30T16:21:08.412818"
    },
    {
        "ticker": "DLR/NOV26",
        "bid": 1621.5,
        "offer": 1626.0,
        "last": "S/D",
        "timestamp": "2026-06-30T16:21:08.412818"
    },
    {
        "ticker": "DLR/ENE27",
        "bid": 1685.0,
        "offer": 1686.0,
        "last": "S/D",
        "timestamp": "2026-06-30T16:21:08.412818"
    },
    {
        "ticker": "DLR/FEB27",
        "bid": 1711.5,
        "offer": 1715.0,
        "last": 1701.0,
        "timestamp": "2026-06-30T16:21:08.412818"
    },
    {
        "ticker": "DLR/MAR27",
        "bid": 1746.0,
        "offer": 1748.0,
        "last": "S/D",
        "timestamp": "2026-06-30T16:21:08.412818"
    },
    {
        "ticker": "DLR/ABR27",
        "bid": 1774.0,
        "offer": 1778.0,
        "last": "S/D",
        "timestamp": "2026-06-30T16:21:08.412818"
    }
]