[
    {
        "ticker": "DLR/ABR26",
        "bid": 1393.0,
        "offer": 1394.0,
        "last": 1401.0,
        "timestamp": "2026-04-29T15:53:48.455362"
    },
    {
        "ticker": "DLR/MAY26",
        "bid": 1414.5,
        "offer": 1415.5,
        "last": 1416.0,
        "timestamp": "2026-04-29T15:53:48.455362"
    },
    {
        "ticker": "DLR/JUN26",
        "bid": 1441.0,
        "offer": 1443.0,
        "last": 1442.0,
        "timestamp": "2026-04-29T15:53:48.455362"
    },
    {
        "ticker": "DLR/JUL26",
        "bid": 1471.0,
        "offer": 1473.5,
        "last": 1486.0,
        "timestamp": "2026-04-29T15:53:48.455362"
    },
    {
        "ticker": "DLR/AGO26",
        "bid": 1504.0,
        "offer": 1507.0,
        "last": "S/D",
        "timestamp": "2026-04-29T15:53:48.455362"
    },
    {
        "ticker": "DLR/OCT26",
        "bid": 1560.0,
        "offer": 1566.0,
        "last": "S/D",
        "timestamp": "2026-04-29T15:53:48.455362"
    },
    {
        "ticker": "DLR/NOV26",
        "bid": 1580.0,
        "offer": 1600.0,
        "last": "S/D",
        "timestamp": "2026-04-29T15:53:48.455362"
    },
    {
        "ticker": "DLR/ENE27",
        "bid": 1640.0,
        "offer": 1660.0,
        "last": "S/D",
        "timestamp": "2026-04-29T15:53:48.455362"
    },
    {
        "ticker": "DLR/FEB27",
        "bid": 1660.0,
        "offer": 1700.0,
        "last": "S/D",
        "timestamp": "2026-04-29T15:53:48.455362"
    },
    {
        "ticker": "DLR/MAR27",
        "bid": 1700.5,
        "offer": 1750.0,
        "last": "S/D",
        "timestamp": "2026-04-29T15:53:48.455362"
    }
]