[
    {
        "ticker": "DLR/ABR26",
        "bid": 1414.5,
        "offer": 1415.0,
        "last": 1411.0,
        "timestamp": "2026-04-27T15:43:49.774231"
    },
    {
        "ticker": "DLR/MAY26",
        "bid": 1436.5,
        "offer": 1437.0,
        "last": 1436.0,
        "timestamp": "2026-04-27T15:43:49.774231"
    },
    {
        "ticker": "DLR/JUN26",
        "bid": 1463.5,
        "offer": 1464.5,
        "last": 1464.0,
        "timestamp": "2026-04-27T15:43:49.774231"
    },
    {
        "ticker": "DLR/JUL26",
        "bid": 1478.5,
        "offer": 1496.0,
        "last": 1471.0,
        "timestamp": "2026-04-27T15:43:49.774231"
    },
    {
        "ticker": "DLR/AGO26",
        "bid": 1520.5,
        "offer": 1529.0,
        "last": "S/D",
        "timestamp": "2026-04-27T15:43:49.774231"
    },
    {
        "ticker": "DLR/OCT26",
        "bid": 1570.0,
        "offer": 1580.0,
        "last": "S/D",
        "timestamp": "2026-04-27T15:43:49.774231"
    },
    {
        "ticker": "DLR/NOV26",
        "bid": 1592.0,
        "offer": 1610.0,
        "last": "S/D",
        "timestamp": "2026-04-27T15:43:49.774231"
    },
    {
        "ticker": "DLR/ENE27",
        "bid": 1658.0,
        "offer": 1675.0,
        "last": "S/D",
        "timestamp": "2026-04-27T15:43:49.774231"
    },
    {
        "ticker": "DLR/FEB27",
        "bid": 1685.0,
        "offer": 1707.5,
        "last": "S/D",
        "timestamp": "2026-04-27T15:43:49.774231"
    },
    {
        "ticker": "DLR/MAR27",
        "bid": 1716.0,
        "offer": 1749.0,
        "last": "S/D",
        "timestamp": "2026-04-27T15:43:49.774231"
    }
]